s2wav/__init__.py
s2wav/filters.py
s2wav/samples.py
s2wav/transforms/__init__.py
s2wav/transforms/base.py
s2wav/transforms/construct.py
s2wav/transforms/wavelet.py
s2wav/transforms/wavelet_c.py
s2wav/transforms/wavelet_precompute.py
s2wav/transforms/wavelet_precompute_torch.py
tests/__init__.py
tests/conftest.py
tests/test_filters.py
tests/test_gradients.py
tests/test_wavelets.py
tests/test_wavelets_base.py
s2wav-1.0.4.dist-info/LICENCE.txt
s2wav-1.0.4.dist-info/METADATA
s2wav-1.0.4.dist-info/WHEEL
s2wav-1.0.4.dist-info/top_level.txt
s2wav-1.0.4.dist-info/RECORD
