Metadata-Version: 2.1
Name: s2wav
Version: 1.0.4
Summary: Differentiable and accelerated wavelet transforms with JAX
Home-page: https://github.com/astro-informatics/s2wav
Author: Authors & Contributors
License: GNU General Public License v3 (GPLv3)
Classifier: Programming Language :: Python :: 3.9
Classifier: Programming Language :: Python :: 3.10
Classifier: Programming Language :: Python :: 3.11
Classifier: Operating System :: OS Independent
Classifier: Intended Audience :: Developers
Classifier: Intended Audience :: Science/Research
Requires-Python: >=3.8
License-File: LICENCE.txt
Requires-Dist: numpy
Requires-Dist: colorlog
Requires-Dist: pyyaml ==6.0
Requires-Dist: scipy
Requires-Dist: s2fft >=1.1.1
